LICENSE
MANIFEST.in
README.md
setup.py
ah/__init__.py
ah.egg-info/PKG-INFO
ah.egg-info/SOURCES.txt
ah.egg-info/dependency_links.txt
ah.egg-info/entry_points.txt
ah.egg-info/requires.txt
ah.egg-info/top_level.txt
ah/ascii/__init__.py
ah/ascii/default.py