Metadata-Version: 2.1
Name: ah
Version: 1.3.1
Summary: ah is a command to display Denis Brogniart in ASCII
Home-page: https://github.com/Sygmei/ah
Author: Sygmei
Author-email: sygmei@sygmei.io
License: UNKNOWN
Project-URL: Bug Reports, https://github.com/Sygmei/ah/issues
Project-URL: Source, https://github.com/ah/PyVili
Keywords: denis brogniart ah meme
Platform: UNKNOWN
Classifier: Development Status :: 3 - Alpha
Classifier: Intended Audience :: Developers
Classifier: Topic :: Software Development :: Build Tools
Classifier: License :: OSI Approved :: MIT License
Classifier: Topic :: Software Development :: Libraries :: Python Modules
Classifier: Programming Language :: Python :: 3
Classifier: Programming Language :: Python :: 3.6
Classifier: Programming Language :: Python :: 3.7
Requires-Python: >=3.6, <4
Provides-Extra: test
